telempack/README.md
telempack/__init__.py
telempack/examples/__init__.py
telempack/examples/example-ddtrace.py
telempack/examples/example-telempack.py
telempack/telemetry/Observer.py
telempack/telemetry/Resource.py
telempack/telemetry/__init__.py
telempack/telemetry/utils/__init__.py
telempack/telemetry/utils/logger.py
telempack-1.3.6.dist-info/LICENSE
telempack-1.3.6.dist-info/METADATA
telempack-1.3.6.dist-info/WHEEL
telempack-1.3.6.dist-info/RECORD
