Metadata-Version: 2.1
Name: telempack
Version: 1.3.6
Summary: A package that uses the OpenTelemetry & Datadog API/SDK to obtain traces, logs, & metrics from services.
Home-page: https://git.eogresources.com/eog/telemetry-py
License: eog
Author: Max Chalitsios
Author-email: Max_Chalitsios@eogresources.com
Requires-Python: ==3.12.4
Classifier: License :: Other/Proprietary License
Classifier: Programming Language :: Python :: 3
Requires-Dist: certifi (==2024.7.4)
Requires-Dist: ddtrace (==2.9.2)
Requires-Dist: fastapi (==0.100.1)
Requires-Dist: httpx (==0.27.0)
Requires-Dist: opentelemetry-api (==1.25.0)
Requires-Dist: opentelemetry-distro (==0.46b0)
Requires-Dist: opentelemetry-instrumentation-aio-pika (==0.46b0)
Requires-Dist: opentelemetry-instrumentation-asgi (==0.46b0)
Requires-Dist: opentelemetry-instrumentation-asyncio (==0.46b0)
Requires-Dist: opentelemetry-instrumentation-confluent-kafka (==0.46b0)
Requires-Dist: opentelemetry-instrumentation-kafka-python (==0.46b0)
Requires-Dist: opentelemetry-instrumentation-mysql (==0.46b0)
Requires-Dist: opentelemetry-instrumentation-mysqlclient (==0.46b0)
Requires-Dist: opentelemetry-instrumentation-psycopg (==0.46b0)
Requires-Dist: opentelemetry-instrumentation-psycopg2 (==0.46b0)
Requires-Dist: opentelemetry-instrumentation-pymemcache (==0.46b0)
Requires-Dist: opentelemetry-instrumentation-pymongo (==0.46b0)
Requires-Dist: opentelemetry-instrumentation-pymysql (==0.46b0)
Requires-Dist: opentelemetry-instrumentation-redis (==0.46b0)
Requires-Dist: opentelemetry-instrumentation-requests (==0.46b0)
Requires-Dist: opentelemetry-instrumentation-sqlalchemy (==0.46b0)
Requires-Dist: opentelemetry-instrumentation-sqlite3 (==0.46b0)
Requires-Dist: opentelemetry-instrumentation-starlette (==0.46b0)
Requires-Dist: opentelemetry-instrumentation-system-metrics (==0.46b0)
Requires-Dist: opentelemetry-instrumentation-threading (==0.46b0)
Requires-Dist: opentelemetry-instrumentation-urllib3 (==0.46b0)
Requires-Dist: opentelemetry-instrumentation-wsgi (==0.46b0)
Requires-Dist: opentelemetry-sdk (==1.25.0)
Requires-Dist: pydantic (==1.10.8)
Requires-Dist: pydantic-core (==2.20.1)
Requires-Dist: pymongo (==4.8.0)
Requires-Dist: twine (==5.1.1)
Project-URL: Repository, https://git.eogresources.com/eog/telemetry-py
